fab_clientlib/__init__.py
fab_clientlib/api_client.py
fab_clientlib/api_response.py
fab_clientlib/configuration.py
fab_clientlib/exceptions.py
fab_clientlib/py.typed
fab_clientlib/rest.py
fab_clientlib/api/__init__.py
fab_clientlib/api/default_api.py
fab_clientlib/models/__init__.py
fab_clientlib/models/api_response.py
fab_clientlib/models/api_response_error.py
fab_clientlib/models/definitions_benchmark_groups_get200_response.py
fab_clientlib/models/definitions_benchmark_groups_get200_response_all_of_body_inner.py
fab_clientlib/models/definitions_benchmarks_get200_response.py
fab_clientlib/models/definitions_benchmarks_get200_response_all_of_body_inner.py
fab_clientlib/models/definitions_fields_field_ids_get200_response.py
fab_clientlib/models/definitions_fields_field_ids_get200_response_all_of_body_inner.py
fab_clientlib/models/definitions_scenarios_scenario_ids_get200_response.py
fab_clientlib/models/definitions_scenarios_scenario_ids_get200_response_all_of_body_inner.py
fab_clientlib/models/definitions_suites_get200_response.py
fab_clientlib/models/definitions_suites_get200_response_all_of_body_inner.py
fab_clientlib/models/definitions_tests_test_ids_get200_response.py
fab_clientlib/models/definitions_tests_test_ids_get200_response_all_of_body_inner.py
fab_clientlib/models/health_live_get200_response.py
fab_clientlib/models/health_live_get200_response_all_of_body.py
fab_clientlib/models/health_live_get200_response_all_of_body_checks_inner.py
fab_clientlib/models/info_get200_response.py
fab_clientlib/models/info_get200_response_all_of_body.py
fab_clientlib/models/results_benchmarks_benchmark_id_tests_test_ids_get200_response.py
fab_clientlib/models/results_benchmarks_benchmark_id_tests_test_ids_get200_response_all_of_body_inner.py
fab_clientlib/models/results_benchmarks_benchmark_ids_get200_response.py
fab_clientlib/models/results_benchmarks_benchmark_ids_get200_response_all_of_body_inner.py
fab_clientlib-0.16.0.dist-info/METADATA
fab_clientlib-0.16.0.dist-info/WHEEL
fab_clientlib-0.16.0.dist-info/top_level.txt
fab_clientlib-0.16.0.dist-info/RECORD
