Metadata-Version: 2.4
Name: fab_clientlib
Version: 0.16.0
Summary: FAB Client Lib
Home-page: https://pypi.org/project/fab-clientlib/
Author: Olivier Stuker, Christian Eichenberger, Manuel Schneider
Author-email: "Olivier Stuker, Christian Eichenberger, Manuel Schneider" <contact@flatland-association.org>
License-Expression: MIT
Project-URL: Repository, https://github.com/flatland-association/flatland-benchmarks
Keywords: OpenAPI,OpenAPI-Generator,FAB Client Lib
Requires-Python: >=3.9
Requires-Dist: urllib3<3.0.0,>=2.1.0
Requires-Dist: python-dateutil>=2.8.2
Requires-Dist: pydantic>=2
Requires-Dist: typing-extensions>=4.7.1
Requires-Dist: lazy-imports<2,>=1
Dynamic: author
Dynamic: home-page
